[
    {
        "name": "Harvey Norman Holdings Ltd",
        "exchange": "ASX",
        "stock": "HVN"
    },
    {
        "name": "JB Hi-Fi Ltd",
        "exchange": "ASX",
        "stock": "JBH"
    },
    {
        "name": "Wesfarmers Ltd",
        "exchange": "ASX",
        "stock": "WES"
    },
    {
        "name": "Woolworths Group Ltd",
        "exchange": "ASX",
        "stock": "WOW"
    },
    {
        "name": "Infosys Ltd - ADR",
        "exchange": "NYSE",
        "stock": "INFY"
    },
    {
        "name": "Zoom Video Communications Inc (All Sessions)",
        "exchange": "NASDAQ",
        "stock": "ZM"
    },
    {
        "name": "QUALCOMM Inc (All Sessions)",
        "exchange": "NASDAQ",
        "stock": "QCOM"
    },
    {
        "name": "Apple Inc (All Sessions)",
        "exchange": "NASDAQ",
        "stock": "AAPL"
    },
    {
        "name": "Amazon.com Inc (All Sessions)",
        "exchange": "NASDAQ",
        "stock": "AMZN"
    },
    {
        "name": "Alphabet Inc - A (All Sessions)",
        "exchange": "NASDAQ",
        "stock": "GOOGL"
    },
    {
        "name": "UnitedHealth Group Inc (All Sessions)",
        "exchange": "NYSE",
        "stock": "UNH"
    },
    {
        "name": "Apple Inc (All Sessions)",
        "exchange": "NASDAQ",
        "stock": "AAPL"
    },
    {
        "name": "Zoom Video Communications Inc (All Sessions)",
        "exchange": "NASDAQ",
        "stock": "ZM"
    },
    {
        "name": "Taiwan Semiconductor Manufacturing Co Ltd - ADR",
        "exchange": "NYSE",
        "stock": "TSM"
    },
    {
        "name": "Accenture PLC",
        "exchange": "NYSE",
        "stock": "ACN"
    },
    {
        "name": "Vanguard S&P 500 Growth ETF",
        "exchange": "NYSE",
        "stock": "VOOG"
    },
    {
        "name": "Boeing Co (All Sessions)",
        "exchange": "NYSE",
        "stock": "BA"
    },
    {
        "name": "Amazon.com Inc (All Sessions)",
        "exchange": "NASDAQ",
        "stock": "AMZN"
    },
    {
        "name": "Vanguard Total Stock Market ETF",
        "exchange": "ASX",
        "stock": "VTS"
    },
    {
        "name": "Walmart Inc (All Sessions)",
        "exchange": "NYSE",
        "stock": "WMT"
    },
    {
        "name": "Appen Limited",
        "exchange": "ASX",
        "stock": "APX"
    }
]
